{
  "repo": "react-router",
  "rootDir": "repos/react-router",
  "filesAnalyzed": 621,
  "totals": {
    "arrayMethod_every": 8,
    "arrayMethod_filter": 106,
    "arrayMethod_find": 20,
    "arrayMethod_findIndex": 11,
    "arrayMethod_flatMap": 10,
    "arrayMethod_map": 187,
    "arrayMethod_reduce": 17,
    "arrayMethod_some": 23,
    "arrowFunctions": 4413,
    "assignOp_%=": 0,
    "assignOp_&&=": 0,
    "assignOp_&=": 0,
    "assignOp_**=": 0,
    "assignOp_*=": 0,
    "assignOp_+=": 106,
    "assignOp_-=": 0,
    "assignOp_/=": 0,
    "assignOp_<<=": 0,
    "assignOp_=": 1371,
    "assignOp_>>=": 0,
    "assignOp_>>>=": 0,
    "assignOp_??=": 3,
    "assignOp_^=": 0,
    "assignOp_|=": 0,
    "assignOp_||=": 1,
    "asyncFunctions": 2272,
    "awaitExpressions": 7113,
    "bigintLiteral": 2,
    "binaryOp_!=": 9,
    "binaryOp_!==": 121,
    "binaryOp_%": 2,
    "binaryOp_&": 0,
    "binaryOp_*": 9,
    "binaryOp_**": 0,
    "binaryOp_+": 250,
    "binaryOp_-": 40,
    "binaryOp_/": 8,
    "binaryOp_<": 19,
    "binaryOp_<<": 0,
    "binaryOp_<=": 8,
    "binaryOp_==": 7,
    "binaryOp_===": 519,
    "binaryOp_>": 45,
    "binaryOp_>=": 13,
    "binaryOp_>>": 0,
    "binaryOp_>>>": 0,
    "binaryOp_^": 0,
    "binaryOp_in": 15,
    "binaryOp_instanceof": 44,
    "binaryOp_|": 0,
    "break": 27,
    "catch": 95,
    "catchNoParam": 9,
    "classAsyncMethods": 12,
    "classDecls": 10,
    "classExtends": 8,
    "classFields": 68,
    "classMethods": 90,
    "classPrivateMembers": 0,
    "classStaticFields": 0,
    "classStaticMethods": 0,
    "continue": 29,
    "destructuringArray": 120,
    "destructuringObject": 339,
    "doWhile": 1,
    "dynamicImports": 49,
    "exportDecls_all": 2,
    "exportDecls_default": 137,
    "exportDecls_named": 460,
    "exportFrom": 111,
    "exportNamedDefault": 1,
    "forAwaitOf": 1,
    "forClassic": 5,
    "forIn": 10,
    "forOf": 129,
    "functions": 889,
    "generatorFunctions": 0,
    "if": 1084,
    "importDecls": 1353,
    "importMeta": 13,
    "importTypeOnly": 207,
    "interpolatedTemplates": 1056,
    "jsxElements": 116,
    "labels": 0,
    "logicalAND": 278,
    "logicalOR": 235,
    "newPromise": 75,
    "nullishCoalescing": 102,
    "numericSeparator": 11,
    "optionalChaining": 613,
    "paramDefault": 69,
    "paramDestructuringArray": 28,
    "paramDestructuringObject": 789,
    "paramRest": 40,
    "promiseAllRaceEtc": 50,
    "regexpFlag_d": 0,
    "regexpFlag_g": 0,
    "regexpFlag_i": 0,
    "regexpFlag_m": 0,
    "regexpFlag_s": 0,
    "regexpFlag_u": 0,
    "regexpFlag_v": 0,
    "regexpFlag_y": 0,
    "regexpLiteral": 0,
    "restElement": 45,
    "return": 1204,
    "spreadElement": 607,
    "switch": 5,
    "switchCases": 17,
    "switchDefault": 2,
    "taggedTemplates": 1133,
    "templateLiterals": 2657,
    "ternary": 353,
    "throw": 237,
    "topLevelAwait": 6,
    "try": 101,
    "tsAsExpression": 283,
    "tsNonNullExpression": 0,
    "tsSatisfiesExpression": 63,
    "tsTypeAssertion": 0,
    "typeAnnotations": 0,
    "updateOp_++": 39,
    "updateOp_--": 1,
    "while": 18,
    "yieldExpressions": 0
  },
  "presence": {
    "arrayMethod_every": 3,
    "arrayMethod_filter": 28,
    "arrayMethod_find": 15,
    "arrayMethod_findIndex": 6,
    "arrayMethod_flatMap": 3,
    "arrayMethod_map": 46,
    "arrayMethod_reduce": 9,
    "arrayMethod_some": 10,
    "arrowFunctions": 245,
    "assignOp_%=": 0,
    "assignOp_&&=": 0,
    "assignOp_&=": 0,
    "assignOp_**=": 0,
    "assignOp_*=": 0,
    "assignOp_+=": 12,
    "assignOp_-=": 0,
    "assignOp_/=": 0,
    "assignOp_<<=": 0,
    "assignOp_=": 182,
    "assignOp_>>=": 0,
    "assignOp_>>>=": 0,
    "assignOp_??=": 2,
    "assignOp_^=": 0,
    "assignOp_|=": 0,
    "assignOp_||=": 1,
    "asyncFunctions": 192,
    "awaitExpressions": 187,
    "bigintLiteral": 1,
    "binaryOp_!=": 4,
    "binaryOp_!==": 33,
    "binaryOp_%": 1,
    "binaryOp_&": 0,
    "binaryOp_*": 6,
    "binaryOp_**": 0,
    "binaryOp_+": 57,
    "binaryOp_-": 16,
    "binaryOp_/": 4,
    "binaryOp_<": 12,
    "binaryOp_<<": 0,
    "binaryOp_<=": 7,
    "binaryOp_==": 5,
    "binaryOp_===": 111,
    "binaryOp_>": 22,
    "binaryOp_>=": 9,
    "binaryOp_>>": 0,
    "binaryOp_>>>": 0,
    "binaryOp_^": 0,
    "binaryOp_in": 9,
    "binaryOp_instanceof": 17,
    "binaryOp_|": 0,
    "break": 9,
    "catch": 37,
    "catchNoParam": 7,
    "classAsyncMethods": 2,
    "classDecls": 10,
    "classExtends": 8,
    "classFields": 8,
    "classMethods": 8,
    "classPrivateMembers": 0,
    "classStaticFields": 0,
    "classStaticMethods": 0,
    "continue": 17,
    "destructuringArray": 14,
    "destructuringObject": 59,
    "doWhile": 1,
    "dynamicImports": 26,
    "exportDecls_all": 1,
    "exportDecls_default": 135,
    "exportDecls_named": 137,
    "exportFrom": 13,
    "exportNamedDefault": 1,
    "forAwaitOf": 1,
    "forClassic": 2,
    "forIn": 6,
    "forOf": 52,
    "functions": 192,
    "generatorFunctions": 0,
    "if": 122,
    "importDecls": 366,
    "importMeta": 10,
    "importTypeOnly": 164,
    "interpolatedTemplates": 118,
    "jsxElements": 12,
    "labels": 0,
    "logicalAND": 55,
    "logicalOR": 70,
    "newPromise": 39,
    "nullishCoalescing": 26,
    "numericSeparator": 6,
    "optionalChaining": 56,
    "paramDefault": 36,
    "paramDestructuringArray": 12,
    "paramDestructuringObject": 122,
    "paramRest": 13,
    "promiseAllRaceEtc": 21,
    "regexpFlag_d": 0,
    "regexpFlag_g": 0,
    "regexpFlag_i": 0,
    "regexpFlag_m": 0,
    "regexpFlag_s": 0,
    "regexpFlag_u": 0,
    "regexpFlag_v": 0,
    "regexpFlag_y": 0,
    "regexpLiteral": 0,
    "restElement": 16,
    "return": 167,
    "spreadElement": 88,
    "switch": 5,
    "switchCases": 5,
    "switchDefault": 2,
    "taggedTemplates": 81,
    "templateLiterals": 172,
    "ternary": 111,
    "throw": 54,
    "topLevelAwait": 4,
    "try": 42,
    "tsAsExpression": 64,
    "tsNonNullExpression": 0,
    "tsSatisfiesExpression": 57,
    "tsTypeAssertion": 0,
    "typeAnnotations": 0,
    "updateOp_++": 15,
    "updateOp_--": 1,
    "while": 14,
    "yieldExpressions": 0
  },
  "perKLOC": {
    "arrayMethod_every": 0.05715142985733574,
    "arrayMethod_filter": 0.7572564456096985,
    "arrayMethod_find": 0.14287857464333933,
    "arrayMethod_findIndex": 0.07858321605383664,
    "arrayMethod_flatMap": 0.07143928732166967,
    "arrayMethod_map": 1.335914672915223,
    "arrayMethod_reduce": 0.12144678844683844,
    "arrayMethod_some": 0.16431036083984024,
    "arrowFunctions": 31.526157495052825,
    "assignOp_%=": 0,
    "assignOp_&&=": 0,
    "assignOp_&=": 0,
    "assignOp_**=": 0,
    "assignOp_*=": 0,
    "assignOp_+=": 0.7572564456096985,
    "assignOp_-=": 0,
    "assignOp_/=": 0,
    "assignOp_<<=": 0,
    "assignOp_=": 9.794326291800912,
    "assignOp_>>=": 0,
    "assignOp_>>>=": 0,
    "assignOp_??=": 0.0214317861965009,
    "assignOp_^=": 0,
    "assignOp_|=": 0,
    "assignOp_||=": 0.007143928732166968,
    "asyncFunctions": 16.23100607948335,
    "awaitExpressions": 50.814765071903636,
    "bigintLiteral": 0.014287857464333935,
    "binaryOp_!=": 0.06429535858950271,
    "binaryOp_!==": 0.864415376592203,
    "binaryOp_%": 0.014287857464333935,
    "binaryOp_&": 0,
    "binaryOp_*": 0.06429535858950271,
    "binaryOp_**": 0,
    "binaryOp_+": 1.7859821830417417,
    "binaryOp_-": 0.28575714928667867,
    "binaryOp_/": 0.05715142985733574,
    "binaryOp_<": 0.13573464591117237,
    "binaryOp_<<": 0,
    "binaryOp_<=": 0.05715142985733574,
    "binaryOp_==": 0.050007501125168774,
    "binaryOp_===": 3.707699011994656,
    "binaryOp_>": 0.3214767929475135,
    "binaryOp_>=": 0.09287107351817057,
    "binaryOp_>>": 0,
    "binaryOp_>>>": 0,
    "binaryOp_^": 0,
    "binaryOp_in": 0.10715893098250451,
    "binaryOp_instanceof": 0.31433286421534656,
    "binaryOp_|": 0,
    "break": 0.1928860757685081,
    "catch": 0.6786732295558618,
    "catchNoParam": 0.06429535858950271,
    "classAsyncMethods": 0.0857271447860036,
    "classDecls": 0.07143928732166967,
    "classExtends": 0.05715142985733574,
    "classFields": 0.48578715378735376,
    "classMethods": 0.642953585895027,
    "classPrivateMembers": 0,
    "classStaticFields": 0,
    "classStaticMethods": 0,
    "continue": 0.20717393323284206,
    "destructuringArray": 0.8572714478600361,
    "destructuringObject": 2.4217918402046017,
    "doWhile": 0.007143928732166968,
    "dynamicImports": 0.3500525078761814,
    "exportDecls_all": 0.014287857464333935,
    "exportDecls_default": 0.9787182363068745,
    "exportDecls_named": 3.286207216796805,
    "exportFrom": 0.7929760892705333,
    "exportNamedDefault": 0.007143928732166968,
    "forAwaitOf": 0.007143928732166968,
    "forClassic": 0.035719643660834834,
    "forIn": 0.07143928732166967,
    "forOf": 0.9215668064495388,
    "functions": 6.350952642896434,
    "generatorFunctions": 0,
    "if": 7.744018745668993,
    "importDecls": 9.665735574621907,
    "importMeta": 0.09287107351817057,
    "importTypeOnly": 1.4787932475585621,
    "interpolatedTemplates": 7.5439887411683175,
    "jsxElements": 0.8286957329313682,
    "labels": 0,
    "logicalAND": 1.9860121875424168,
    "logicalOR": 1.6788232520592372,
    "newPromise": 0.5357946549125225,
    "nullishCoalescing": 0.7286807306810307,
    "numericSeparator": 0.07858321605383664,
    "optionalChaining": 4.379228312818351,
    "paramDefault": 0.4929310825195207,
    "paramDestructuringArray": 0.2000300045006751,
    "paramDestructuringObject": 5.636559769679737,
    "paramRest": 0.28575714928667867,
    "promiseAllRaceEtc": 0.3571964366083484,
    "regexpFlag_d": 0,
    "regexpFlag_g": 0,
    "regexpFlag_i": 0,
    "regexpFlag_m": 0,
    "regexpFlag_s": 0,
    "regexpFlag_u": 0,
    "regexpFlag_v": 0,
    "regexpFlag_y": 0,
    "regexpLiteral": 0,
    "restElement": 0.3214767929475135,
    "return": 8.601290193529028,
    "spreadElement": 4.336364740425349,
    "switch": 0.035719643660834834,
    "switchCases": 0.12144678844683844,
    "switchDefault": 0.014287857464333935,
    "taggedTemplates": 8.094071253545174,
    "templateLiterals": 18.981418641367632,
    "ternary": 2.5218068424549394,
    "throw": 1.6931111095235711,
    "topLevelAwait": 0.0428635723930018,
    "try": 0.7215368019488637,
    "tsAsExpression": 2.0217318312032515,
    "tsNonNullExpression": 0,
    "tsSatisfiesExpression": 0.4500675101265189,
    "tsTypeAssertion": 0,
    "typeAnnotations": 0,
    "updateOp_++": 0.2786132205545117,
    "updateOp_--": 0.007143928732166968,
    "while": 0.12859071717900541,
    "yieldExpressions": 0
  },
  "locTotal": 139979,
  "totalOccurrences": 32264,
  "featuresCatalog": {
    "arrayMethod_every": true,
    "arrayMethod_filter": true,
    "arrayMethod_find": true,
    "arrayMethod_findIndex": true,
    "arrayMethod_flatMap": true,
    "arrayMethod_map": true,
    "arrayMethod_reduce": true,
    "arrayMethod_some": true,
    "arrowFunctions": true,
    "assignOp_%=": true,
    "assignOp_&&=": true,
    "assignOp_&=": true,
    "assignOp_**=": true,
    "assignOp_*=": true,
    "assignOp_+=": true,
    "assignOp_-=": true,
    "assignOp_/=": true,
    "assignOp_<<=": true,
    "assignOp_=": true,
    "assignOp_>>=": true,
    "assignOp_>>>=": true,
    "assignOp_??=": true,
    "assignOp_^=": true,
    "assignOp_|=": true,
    "assignOp_||=": true,
    "asyncFunctions": true,
    "awaitExpressions": true,
    "bigintLiteral": true,
    "binaryOp_!=": true,
    "binaryOp_!==": true,
    "binaryOp_%": true,
    "binaryOp_&": true,
    "binaryOp_*": true,
    "binaryOp_**": true,
    "binaryOp_+": true,
    "binaryOp_-": true,
    "binaryOp_/": true,
    "binaryOp_<": true,
    "binaryOp_<<": true,
    "binaryOp_<=": true,
    "binaryOp_==": true,
    "binaryOp_===": true,
    "binaryOp_>": true,
    "binaryOp_>=": true,
    "binaryOp_>>": true,
    "binaryOp_>>>": true,
    "binaryOp_^": true,
    "binaryOp_in": true,
    "binaryOp_instanceof": true,
    "binaryOp_|": true,
    "break": true,
    "catch": true,
    "catchNoParam": true,
    "classAsyncMethods": true,
    "classDecls": true,
    "classExtends": true,
    "classFields": true,
    "classMethods": true,
    "classPrivateMembers": true,
    "classStaticFields": true,
    "classStaticMethods": true,
    "continue": true,
    "destructuringArray": true,
    "destructuringObject": true,
    "doWhile": true,
    "dynamicImports": true,
    "exportDecls_all": true,
    "exportDecls_default": true,
    "exportDecls_named": true,
    "exportFrom": true,
    "exportNamedDefault": true,
    "forAwaitOf": true,
    "forClassic": true,
    "forIn": true,
    "forOf": true,
    "functions": true,
    "generatorFunctions": true,
    "if": true,
    "importDecls": true,
    "importMeta": true,
    "importTypeOnly": true,
    "interpolatedTemplates": true,
    "jsxElements": true,
    "labels": true,
    "logicalAND": true,
    "logicalOR": true,
    "newPromise": true,
    "nullishCoalescing": true,
    "numericSeparator": true,
    "optionalChaining": true,
    "paramDefault": true,
    "paramDestructuringArray": true,
    "paramDestructuringObject": true,
    "paramRest": true,
    "promiseAllRaceEtc": true,
    "regexpFlag_d": true,
    "regexpFlag_g": true,
    "regexpFlag_i": true,
    "regexpFlag_m": true,
    "regexpFlag_s": true,
    "regexpFlag_u": true,
    "regexpFlag_v": true,
    "regexpFlag_y": true,
    "regexpLiteral": true,
    "restElement": true,
    "return": true,
    "spreadElement": true,
    "switch": true,
    "switchCases": true,
    "switchDefault": true,
    "taggedTemplates": true,
    "templateLiterals": true,
    "ternary": true,
    "throw": true,
    "topLevelAwait": true,
    "try": true,
    "tsAsExpression": true,
    "tsNonNullExpression": true,
    "tsSatisfiesExpression": true,
    "tsTypeAssertion": true,
    "typeAnnotations": true,
    "updateOp_++": true,
    "updateOp_--": true,
    "while": true,
    "yieldExpressions": true
  },
  "featuresTotal": 125,
  "featuresObserved": 88,
  "missingDetectors": {
    "SequenceExpression": {
      "visited": 22326
    },
    "Function": {
      "visited": 5302
    },
    "MemberExpression": {
      "visited": 34741
    },
    "VariableDeclaration": {
      "visited": 7010
    },
    "ImportNamespaceSpecifier": {
      "visited": 81
    },
    "ImportSpecifier": {
      "visited": 1599
    },
    "ImportDefaultSpecifier": {
      "visited": 345
    },
    "TSInterfaceDeclaration": {
      "visited": 46
    },
    "TSModuleDeclaration": {
      "visited": 13
    },
    "UnaryExpression": {
      "visited": 557
    },
    "JSXIdentifier": {
      "visited": 259
    },
    "JSXOpeningElement": {
      "visited": 116
    },
    "JSXText": {
      "visited": 170
    },
    "JSXAttribute": {
      "visited": 52
    },
    "JSXExpressionContainer": {
      "visited": 44
    },
    "JSXClosingElement": {
      "visited": 85
    },
    "JSXEmptyExpression": {
      "visited": 5
    },
    "JSXMemberExpression": {
      "visited": 6
    },
    "ObjectPattern": {
      "visited": 1140
    },
    "AssignmentPattern": {
      "visited": 102
    },
    "TSTypeAliasDeclaration": {
      "visited": 135
    },
    "TSNonNullExpression": {
      "visited": 70
    },
    "ThisExpression": {
      "visited": 550
    },
    "Super": {
      "visited": 11
    },
    "TSDeclareFunction": {
      "visited": 9
    }
  },
  "totalMissingDetections": 74774,
  "generatedAt": "2025-10-05T22:37:22.222Z"
}